color_codes/__init__.py
color_codes-0.0.1.dist-info/LICENSE
color_codes-0.0.1.dist-info/METADATA
color_codes-0.0.1.dist-info/WHEEL
color_codes-0.0.1.dist-info/top_level.txt
color_codes-0.0.1.dist-info/RECORD
