Metadata-Version: 2.1
Name: color-codes
Version: 0.0.1
Summary: Simple package for using the color codes any where
Home-page: UNKNOWN
Author: Danish Anodher
Author-email: danishkh253@gmail.com
License: UNKNOWN
Platform: UNKNOWN
Classifier: Programming Language :: Python :: 3
Classifier: License :: OSI Approved :: MIT License
Classifier: Operating System :: OS Independent
License-File: LICENSE
